gateway/__init__.py
gateway/gateway.py
gateway/gatewaybus.py
pcan_gatewaybus-0.0.2.dist-info/LICENSE
pcan_gatewaybus-0.0.2.dist-info/METADATA
pcan_gatewaybus-0.0.2.dist-info/WHEEL
pcan_gatewaybus-0.0.2.dist-info/entry_points.txt
pcan_gatewaybus-0.0.2.dist-info/top_level.txt
pcan_gatewaybus-0.0.2.dist-info/RECORD
