Metadata-Version: 2.1
Name: pcan-gatewaybus
Version: 0.0.2
Summary: pcan gatewaybus backend for "python-can"
Home-page: https://github.com/ys-oh/python-pcan-gatewaybus
Author: yunsik oh
Author-email: oyster90@naver.com
Classifier: Environment :: Console
Classifier: Programming Language :: Python :: 3
Classifier: License :: OSI Approved :: GNU General Public License v3 (GPLv3)
License-File: LICENSE
Requires-Dist: python-can
